autoreduce_db/__init__.py
autoreduce_db/manage.py
autoreduce_db/autoreduce_django/__init__.py
autoreduce_db/autoreduce_django/asgi.py
autoreduce_db/autoreduce_django/settings.py
autoreduce_db/autoreduce_django/urls.py
autoreduce_db/autoreduce_django/wsgi.py
autoreduce_db/instrument/__init__.py
autoreduce_db/instrument/models.py
autoreduce_db/instrument/migrations/0001_initial.py
autoreduce_db/instrument/migrations/0002_alter_variable_value.py
autoreduce_db/instrument/migrations/0002_auto_20210426_1519.py
autoreduce_db/instrument/migrations/0003_merge_20210426_1528.py
autoreduce_db/instrument/migrations/0004_auto_20210426_1600.py
autoreduce_db/instrument/migrations/__init__.py
autoreduce_db/reduction_viewer/__init__.py
autoreduce_db/reduction_viewer/models.py
autoreduce_db/reduction_viewer/migrations/0001_initial.py
autoreduce_db/reduction_viewer/migrations/0002_remove_reductionrun_cancel.py
autoreduce_db/reduction_viewer/migrations/0003_auto_20210310_1601.py
autoreduce_db/reduction_viewer/migrations/0004_instrument_is_flat_output.py
autoreduce_db/reduction_viewer/migrations/0005_auto_20210326_1628.py
autoreduce_db/reduction_viewer/migrations/0006_reductionrun_reduction_host.py
autoreduce_db/reduction_viewer/migrations/__init__.py
autoreduce_db-0.1.4.dist-info/METADATA
autoreduce_db-0.1.4.dist-info/WHEEL
autoreduce_db-0.1.4.dist-info/top_level.txt
autoreduce_db-0.1.4.dist-info/RECORD
