Metadata-Version: 2.1
Name: autoreduce-db
Version: 0.1.4
Summary: ISIS Autoreduce
Home-page: https://github.com/ISISScientificComputing/autoreduce-db/
Author: ISIS Autoreduction Team
License: UNKNOWN
Platform: UNKNOWN
Requires-Dist: autoreduce-utils (==0.1.3)
Requires-Dist: Django (==3.2.2)
